{
  "info" : [
    {
      "title":"Lorem Ipsom 1",
      "title1" : "Code:",
      "data1" : "ABC123",
      "title2" : "Branches:",
      "data2" : "A,C,M",
      "title3" : "Affiliated:",
      "data3" : "Lorem Ipsom Tech Global University",
      "title4" : "Address:",
      "data4" : "123,Street No.12,State - pincode",
      "title5" : "Contact No.",
      "data5" : "+91 9876543210",
      "title6" : "Email Id:",
      "data6": "email@gmail.com"
    },
    {
      "title":"Lorem Ipsom 2",
      "title1" : "Code:",
      "data1" : "ABC123",
      "title2" : "Branches:",
      "data2" : "A,C,M",
      "title3" : "Affiliated:",
      "data3" : "Lorem Ipsom Tech Global University",
      "title4" : "Address:",
      "data4" : "123,Street No.12,State - pincode",
      "title5" : "Contact No.",
      "data5" : "+91 9876543210",
      "title6" : "Email Id:",
      "data6": "email@gmail.com"
    },
    {
      "title":"Lorem Ipsom 3",
      "title1" : "Code:",
      "data1" : "ABC123",
      "title2" : "Branches:",
      "data2" : "A,C,M",
      "title3" : "Affiliated:",
      "data3" : "Lorem Ipsom Tech Global University",
      "title4" : "Address:",
      "data4" : "123,Street No.12,State - pincode",
      "title5" : "Contact No.",
      "data5" : "+91 9876543210",
      "title6" : "Email Id:",
      "data6": "email@gmail.com"
    },
    {
      "title":"Lorem Ipsom 4",
      "title1" : "Code:",
      "data1" : "ABC123",
      "title2" : "Branches:",
      "data2" : "A,C,M",
      "title3" : "Affiliated:",
      "data3" : "Lorem Ipsom Tech Global University",
      "title4" : "Address:",
      "data4" : "123,Street No.12,State - pincode",
      "title5" : "Contact No.",
      "data5" : "+91 9876543210",
      "title6" : "Email Id:",
      "data6": "email@gmail.com"
    },
    {
      "title":"Mallareddy Engineering College",
      "title1" : "Code:",
      "data1" : "ABC123",
      "title2" : "Branches:",
      "data2" : "A,C,M",
      "title3" : "Affiliated:",
      "data3" : "Lorem Ipsom Tech Global University",
      "title4" : "Address:",
      "data4" : "123,Street No.12,Street Name,\n Area,State - pincode",
      "title5" : "Contact No.",
      "data5" : "+91 9876543210",
      "title6" : "Email Id:",
      "data6": "email@gmail.com"
    },
    {
      "title":"Lorem Ipsom 6",
      "title1" : "Code:",
      "data1" : "ABC123",
      "title2" : "Branches:",
      "data2" : "A,C,M",
      "title3" : "Affiliated:",
      "data3" : "Lorem Ipsom Tech Global University",
      "title4" : "Address:",
      "data4" : "123,Street No.12,Street Name,\n Area,State - pincode",
      "title5" : "Contact No.",
      "data5" : "+91 9876543210",
      "title6" : "Email Id:",
      "data6": "email@gmail.com"
    },
    {
      "title":"Lorem Ipsom 7",
      "title1" : "Code:",
      "data1" : "ABC123",
      "title2" : "Branches:",
      "data2" : "A,C,M",
      "title3" : "Affiliated:",
      "data3" : "Lorem Ipsom Tech Global University",
      "title4" : "Address:",
      "data4" : "123,Street No.12,Street Name,\n Area,State - pincode",
      "title5" : "Contact No.",
      "data5" : "+91 9876543210",
      "title6" : "Email Id:",
      "data6": "email@gmail.com"
    }
  ]
}